{
  "updated_at": "2026-07-09T02:20:07.203430+00:00",
  "assets": [
    {
      "asset": "BTC",
      "price": 62065.56,
      "poly_up": 0.8,
      "poly_down": 0.21,
      "poly_open": 61916.0,
      "kalshi_levels": 10,
      "kalshi_raw": [
        {
          "t": 61400.0,
          "ya": 0.99,
          "na": 0.02
        },
        {
          "t": 61600.0,
          "ya": 0.98,
          "na": 0.03
        },
        {
          "t": 61700.0,
          "ya": 0.94,
          "na": 0.07
        },
        {
          "t": 61800.0,
          "ya": 0.86,
          "na": 0.15
        },
        {
          "t": 61900.0,
          "ya": 0.71,
          "na": 0.3
        },
        {
          "t": 62000.0,
          "ya": 0.52,
          "na": 0.49
        },
        {
          "t": 62100.0,
          "ya": 0.3,
          "na": 0.71
        },
        {
          "t": 62200.0,
          "ya": 0.15,
          "na": 0.86
        },
        {
          "t": 62300.0,
          "ya": 0.07,
          "na": 0.94
        },
        {
          "t": 62400.0,
          "ya": 0.03,
          "na": 0.98
        }
      ],
      "trades": [
        {
          "direction": "UP + NO",
          "kalshi_level": 61800.0,
          "poly_price": 0.8,
          "kalshi_price": 0.15,
          "cost": 0.95,
          "profit_pct": 5.3,
          "dead_zone": 116.0,
          "units": 5,
          "deploy_dollars": 4.75,
          "kalshi_vol": 105612.59,
          "close_time": "2026-07-09T03:00:00Z",
          "qualified": false,
          "block_reason": "DZ $116 > max $40"
        },
        {
          "direction": "DOWN + YES",
          "kalshi_level": 61900.0,
          "poly_price": 0.21,
          "kalshi_price": 0.71,
          "cost": 0.92,
          "profit_pct": 8.7,
          "dead_zone": 0.0,
          "units": 5,
          "deploy_dollars": 4.6,
          "kalshi_vol": 121592.21,
          "close_time": "2026-07-09T03:00:00Z",
          "qualified": false,
          "block_reason": "profit 8.7% < min 12%"
        }
      ]
    },
    {
      "asset": "ETH",
      "price": 1736.64,
      "poly_up": 0.82,
      "poly_down": 0.19,
      "poly_open": 1731.8,
      "kalshi_levels": 75,
      "kalshi_raw": [
        {
          "t": 1010.0,
          "ya": 1.0,
          "na": 0.01
        },
        {
          "t": 1030.0,
          "ya": 1.0,
          "na": 0.01
        },
        {
          "t": 1050.0,
          "ya": 1.0,
          "na": 0.01
        },
        {
          "t": 1070.0,
          "ya": 1.0,
          "na": 0.01
        },
        {
          "t": 1090.0,
          "ya": 1.0,
          "na": 0.01
        },
        {
          "t": 1110.0,
          "ya": 1.0,
          "na": 0.01
        },
        {
          "t": 1130.0,
          "ya": 1.0,
          "na": 0.01
        },
        {
          "t": 1150.0,
          "ya": 1.0,
          "na": 0.01
        },
        {
          "t": 1170.0,
          "ya": 1.0,
          "na": 0.01
        },
        {
          "t": 1190.0,
          "ya": 1.0,
          "na": 0.01
        },
        {
          "t": 1210.0,
          "ya": 1.0,
          "na": 0.01
        },
        {
          "t": 1230.0,
          "ya": 1.0,
          "na": 0.01
        },
        {
          "t": 1250.0,
          "ya": 1.0,
          "na": 0.01
        },
        {
          "t": 1270.0,
          "ya": 1.0,
          "na": 0.01
        },
        {
          "t": 1290.0,
          "ya": 1.0,
          "na": 0.01
        },
        {
          "t": 1310.0,
          "ya": 1.0,
          "na": 0.01
        },
        {
          "t": 1330.0,
          "ya": 1.0,
          "na": 0.01
        },
        {
          "t": 1350.0,
          "ya": 1.0,
          "na": 0.01
        },
        {
          "t": 1370.0,
          "ya": 1.0,
          "na": 0.01
        },
        {
          "t": 1390.0,
          "ya": 1.0,
          "na": 0.01
        },
        {
          "t": 1410.0,
          "ya": 1.0,
          "na": 0.01
        },
        {
          "t": 1430.0,
          "ya": 1.0,
          "na": 0.01
        },
        {
          "t": 1450.0,
          "ya": 1.0,
          "na": 0.01
        },
        {
          "t": 1470.0,
          "ya": 1.0,
          "na": 0.01
        },
        {
          "t": 1490.0,
          "ya": 1.0,
          "na": 0.01
        },
        {
          "t": 1510.0,
          "ya": 1.0,
          "na": 0.01
        },
        {
          "t": 1530.0,
          "ya": 1.0,
          "na": 0.01
        },
        {
          "t": 1550.0,
          "ya": 1.0,
          "na": 0.01
        },
        {
          "t": 1570.0,
          "ya": 1.0,
          "na": 0.01
        },
        {
          "t": 1590.0,
          "ya": 1.0,
          "na": 0.01
        },
        {
          "t": 1610.0,
          "ya": 1.0,
          "na": 0.01
        },
        {
          "t": 1630.0,
          "ya": 1.0,
          "na": 0.01
        },
        {
          "t": 1650.0,
          "ya": 1.0,
          "na": 0.01
        },
        {
          "t": 1670.0,
          "ya": 1.0,
          "na": 0.01
        },
        {
          "t": 1690.0,
          "ya": 1.0,
          "na": 0.01
        },
        {
          "t": 1710.0,
          "ya": 1.0,
          "na": 0.01
        },
        {
          "t": 1730.0,
          "ya": 0.79,
          "na": 0.22
        },
        {
          "t": 1750.0,
          "ya": 0.03,
          "na": 0.98
        },
        {
          "t": 1770.0,
          "ya": 0.01,
          "na": 1.0
        },
        {
          "t": 1790.0,
          "ya": 0.01,
          "na": 1.0
        },
        {
          "t": 1810.0,
          "ya": 0.01,
          "na": 1.0
        },
        {
          "t": 1830.0,
          "ya": 0.01,
          "na": 1.0
        },
        {
          "t": 1850.0,
          "ya": 0.01,
          "na": 1.0
        },
        {
          "t": 1870.0,
          "ya": 0.01,
          "na": 1.0
        },
        {
          "t": 1890.0,
          "ya": 0.01,
          "na": 1.0
        },
        {
          "t": 1910.0,
          "ya": 0.01,
          "na": 1.0
        },
        {
          "t": 1930.0,
          "ya": 0.01,
          "na": 1.0
        },
        {
          "t": 1950.0,
          "ya": 0.01,
          "na": 1.0
        },
        {
          "t": 1970.0,
          "ya": 0.01,
          "na": 1.0
        },
        {
          "t": 1990.0,
          "ya": 0.01,
          "na": 1.0
        },
        {
          "t": 2010.0,
          "ya": 0.01,
          "na": 1.0
        },
        {
          "t": 2030.0,
          "ya": 0.01,
          "na": 1.0
        },
        {
          "t": 2050.0,
          "ya": 0.01,
          "na": 1.0
        },
        {
          "t": 2070.0,
          "ya": 0.01,
          "na": 1.0
        },
        {
          "t": 2090.0,
          "ya": 0.01,
          "na": 1.0
        },
        {
          "t": 2110.0,
          "ya": 0.01,
          "na": 1.0
        },
        {
          "t": 2130.0,
          "ya": 0.01,
          "na": 1.0
        },
        {
          "t": 2150.0,
          "ya": 0.01,
          "na": 1.0
        },
        {
          "t": 2170.0,
          "ya": 0.01,
          "na": 1.0
        },
        {
          "t": 2190.0,
          "ya": 0.01,
          "na": 1.0
        },
        {
          "t": 2210.0,
          "ya": 0.01,
          "na": 1.0
        },
        {
          "t": 2230.0,
          "ya": 0.01,
          "na": 1.0
        },
        {
          "t": 2250.0,
          "ya": 0.01,
          "na": 1.0
        },
        {
          "t": 2270.0,
          "ya": 0.01,
          "na": 1.0
        },
        {
          "t": 2290.0,
          "ya": 0.01,
          "na": 1.0
        },
        {
          "t": 2310.0,
          "ya": 0.01,
          "na": 1.0
        },
        {
          "t": 2330.0,
          "ya": 0.01,
          "na": 1.0
        },
        {
          "t": 2350.0,
          "ya": 0.01,
          "na": 1.0
        },
        {
          "t": 2370.0,
          "ya": 0.01,
          "na": 1.0
        },
        {
          "t": 2390.0,
          "ya": 0.01,
          "na": 1.0
        },
        {
          "t": 2410.0,
          "ya": 0.01,
          "na": 1.0
        },
        {
          "t": 2430.0,
          "ya": 0.01,
          "na": 1.0
        },
        {
          "t": 2450.0,
          "ya": 0.01,
          "na": 1.0
        },
        {
          "t": 2470.0,
          "ya": 0.01,
          "na": 1.0
        },
        {
          "t": 2490.0,
          "ya": 0.01,
          "na": 1.0
        }
      ],
      "trades": [
        {
          "direction": "UP + NO",
          "kalshi_level": 1710.0,
          "poly_price": 0.82,
          "kalshi_price": 0.01,
          "cost": 0.83,
          "profit_pct": 20.5,
          "dead_zone": 21.8,
          "units": 5,
          "deploy_dollars": 4.15,
          "kalshi_vol": 5571.51,
          "close_time": null,
          "qualified": true,
          "block_reason": null
        },
        {
          "direction": "DOWN + YES",
          "kalshi_level": 1750.0,
          "poly_price": 0.19,
          "kalshi_price": 0.03,
          "cost": 0.22,
          "profit_pct": 354.5,
          "dead_zone": 18.2,
          "units": 9,
          "deploy_dollars": 1.98,
          "kalshi_vol": 7733.51,
          "close_time": null,
          "qualified": true,
          "block_reason": null
        }
      ]
    }
  ]
}