{
  "updated_at": "2026-06-24T20:50:07.798266+00:00",
  "assets": [
    {
      "asset": "ETH",
      "price": 1620.04,
      "poly_up": 0.999,
      "poly_down": 0.004,
      "poly_open": 1584.59,
      "kalshi_levels": 40,
      "kalshi_raw": [
        {
          "t": 800.0,
          "ya": 1.0,
          "na": 0.01
        },
        {
          "t": 840.0,
          "ya": 1.0,
          "na": 0.01
        },
        {
          "t": 880.0,
          "ya": 1.0,
          "na": 0.01
        },
        {
          "t": 920.0,
          "ya": 1.0,
          "na": 0.01
        },
        {
          "t": 960.0,
          "ya": 1.0,
          "na": 0.01
        },
        {
          "t": 1000.0,
          "ya": 1.0,
          "na": 0.01
        },
        {
          "t": 1040.0,
          "ya": 1.0,
          "na": 0.01
        },
        {
          "t": 1080.0,
          "ya": 1.0,
          "na": 0.01
        },
        {
          "t": 1120.0,
          "ya": 1.0,
          "na": 0.01
        },
        {
          "t": 1160.0,
          "ya": 1.0,
          "na": 0.01
        },
        {
          "t": 1200.0,
          "ya": 1.0,
          "na": 0.01
        },
        {
          "t": 1240.0,
          "ya": 1.0,
          "na": 0.01
        },
        {
          "t": 1280.0,
          "ya": 1.0,
          "na": 0.01
        },
        {
          "t": 1320.0,
          "ya": 1.0,
          "na": 0.01
        },
        {
          "t": 1360.0,
          "ya": 1.0,
          "na": 0.01
        },
        {
          "t": 1400.0,
          "ya": 1.0,
          "na": 0.01
        },
        {
          "t": 1440.0,
          "ya": 1.0,
          "na": 0.01
        },
        {
          "t": 1480.0,
          "ya": 1.0,
          "na": 0.01
        },
        {
          "t": 1520.0,
          "ya": 1.0,
          "na": 0.01
        },
        {
          "t": 1560.0,
          "ya": 1.0,
          "na": 0.01
        },
        {
          "t": 1600.0,
          "ya": 0.98,
          "na": 0.03
        },
        {
          "t": 1640.0,
          "ya": 0.01,
          "na": 1.0
        },
        {
          "t": 1680.0,
          "ya": 0.01,
          "na": 1.0
        },
        {
          "t": 1720.0,
          "ya": 0.01,
          "na": 1.0
        },
        {
          "t": 1760.0,
          "ya": 0.01,
          "na": 1.0
        },
        {
          "t": 1800.0,
          "ya": 0.01,
          "na": 1.0
        },
        {
          "t": 1840.0,
          "ya": 0.01,
          "na": 1.0
        },
        {
          "t": 1880.0,
          "ya": 0.01,
          "na": 1.0
        },
        {
          "t": 1920.0,
          "ya": 0.01,
          "na": 1.0
        },
        {
          "t": 1960.0,
          "ya": 0.01,
          "na": 1.0
        },
        {
          "t": 2000.0,
          "ya": 0.01,
          "na": 1.0
        },
        {
          "t": 2040.0,
          "ya": 0.01,
          "na": 1.0
        },
        {
          "t": 2080.0,
          "ya": 0.01,
          "na": 1.0
        },
        {
          "t": 2120.0,
          "ya": 0.01,
          "na": 1.0
        },
        {
          "t": 2160.0,
          "ya": 0.01,
          "na": 1.0
        },
        {
          "t": 2200.0,
          "ya": 0.01,
          "na": 1.0
        },
        {
          "t": 2240.0,
          "ya": 0.01,
          "na": 1.0
        },
        {
          "t": 2280.0,
          "ya": 0.01,
          "na": 1.0
        },
        {
          "t": 2320.0,
          "ya": 0.01,
          "na": 1.0
        },
        {
          "t": 2360.0,
          "ya": 0.01,
          "na": 1.0
        }
      ],
      "trades": [
        {
          "direction": "UP + NO",
          "qualified": false,
          "block_reason": "no arb (cost \u2265 $1 on all levels)",
          "dead_zone": null,
          "profit_pct": null,
          "cost": null,
          "deploy_dollars": null
        },
        {
          "direction": "DOWN + YES",
          "kalshi_level": 1600.0,
          "poly_price": 0.004,
          "kalshi_price": 0.98,
          "cost": 0.984,
          "profit_pct": 1.6,
          "dead_zone": 15.41,
          "units": 5,
          "deploy_dollars": 4.92,
          "kalshi_vol": 52773.56,
          "close_time": null,
          "qualified": false,
          "block_reason": "profit 1.6% < min 12%"
        }
      ]
    }
  ]
}