{
  "updated_at": "2026-04-19T03:35:07.547962+00:00",
  "assets": [
    {
      "asset": "BTC",
      "price": 75556.0,
      "poly_up": 0.77,
      "poly_down": 0.24,
      "poly_open": 75496.01,
      "kalshi_levels": 0,
      "trades": [
        {
          "direction": "UP + NO",
          "qualified": false,
          "block_reason": "no arb (cost \u2265 $1 on all levels)",
          "dead_zone": null,
          "profit_pct": null,
          "cost": null,
          "deploy_dollars": null
        },
        {
          "direction": "DOWN + YES",
          "qualified": false,
          "block_reason": "no arb (cost \u2265 $1 on all levels)",
          "dead_zone": null,
          "profit_pct": null,
          "cost": null,
          "deploy_dollars": null
        }
      ]
    },
    {
      "asset": "ETH",
      "price": 2342.01,
      "poly_up": 0.89,
      "poly_down": 0.12,
      "poly_open": 2338.24,
      "kalshi_levels": 0,
      "trades": [
        {
          "direction": "UP + NO",
          "qualified": false,
          "block_reason": "no arb (cost \u2265 $1 on all levels)",
          "dead_zone": null,
          "profit_pct": null,
          "cost": null,
          "deploy_dollars": null
        },
        {
          "direction": "DOWN + YES",
          "qualified": false,
          "block_reason": "no arb (cost \u2265 $1 on all levels)",
          "dead_zone": null,
          "profit_pct": null,
          "cost": null,
          "deploy_dollars": null
        }
      ]
    }
  ]
}