{
  "updated_at": "2026-06-19T03:20:07.257399+00:00",
  "assets": [
    {
      "asset": "BTC",
      "price": 62543.3,
      "poly_up": 0.039,
      "poly_down": 0.962,
      "poly_open": 63006.01,
      "kalshi_levels": 0,
      "kalshi_raw": [],
      "trades": [
        {
          "direction": "UP + NO",
          "qualified": false,
          "block_reason": "no arb (cost \u2265 $1 on all levels)",
          "dead_zone": null,
          "profit_pct": null,
          "cost": null,
          "deploy_dollars": null
        },
        {
          "direction": "DOWN + YES",
          "qualified": false,
          "block_reason": "no arb (cost \u2265 $1 on all levels)",
          "dead_zone": null,
          "profit_pct": null,
          "cost": null,
          "deploy_dollars": null
        }
      ]
    },
    {
      "asset": "ETH",
      "price": 1689.66,
      "poly_up": 0.03,
      "poly_down": 0.976,
      "poly_open": 1707.15,
      "kalshi_levels": 0,
      "kalshi_raw": [],
      "trades": [
        {
          "direction": "UP + NO",
          "qualified": false,
          "block_reason": "no arb (cost \u2265 $1 on all levels)",
          "dead_zone": null,
          "profit_pct": null,
          "cost": null,
          "deploy_dollars": null
        },
        {
          "direction": "DOWN + YES",
          "qualified": false,
          "block_reason": "no arb (cost \u2265 $1 on all levels)",
          "dead_zone": null,
          "profit_pct": null,
          "cost": null,
          "deploy_dollars": null
        }
      ]
    }
  ]
}