{
  "updated_at": "2026-05-05T03:35:07.214732+00:00",
  "assets": [
    {
      "asset": "BTC",
      "price": 80842.84,
      "poly_up": 0.95,
      "poly_down": 0.06,
      "poly_open": 80554.69,
      "kalshi_levels": 0,
      "kalshi_raw": [],
      "trades": [
        {
          "direction": "UP + NO",
          "qualified": false,
          "block_reason": "no arb (cost \u2265 $1 on all levels)",
          "dead_zone": null,
          "profit_pct": null,
          "cost": null,
          "deploy_dollars": null
        },
        {
          "direction": "DOWN + YES",
          "qualified": false,
          "block_reason": "no arb (cost \u2265 $1 on all levels)",
          "dead_zone": null,
          "profit_pct": null,
          "cost": null,
          "deploy_dollars": null
        }
      ]
    },
    {
      "asset": "ETH",
      "price": 2380.01,
      "poly_up": 0.92,
      "poly_down": 0.09,
      "poly_open": 2367.72,
      "kalshi_levels": 0,
      "kalshi_raw": [],
      "trades": [
        {
          "direction": "UP + NO",
          "qualified": false,
          "block_reason": "no arb (cost \u2265 $1 on all levels)",
          "dead_zone": null,
          "profit_pct": null,
          "cost": null,
          "deploy_dollars": null
        },
        {
          "direction": "DOWN + YES",
          "qualified": false,
          "block_reason": "no arb (cost \u2265 $1 on all levels)",
          "dead_zone": null,
          "profit_pct": null,
          "cost": null,
          "deploy_dollars": null
        }
      ]
    }
  ]
}