{
  "updated_at": "2026-06-14T13:50:06.783303+00:00",
  "assets": [
    {
      "asset": "BTC",
      "price": 64303.47,
      "poly_up": 0.37,
      "poly_down": 0.64,
      "poly_open": 64327.54,
      "kalshi_levels": 3,
      "kalshi_raw": [
        {
          "t": 64200.0,
          "ya": 0.93,
          "na": 0.08
        },
        {
          "t": 64300.0,
          "ya": 0.36,
          "na": 0.65
        },
        {
          "t": 64400.0,
          "ya": 0.03,
          "na": 0.98
        }
      ],
      "trades": [
        {
          "direction": "UP + NO",
          "kalshi_level": 64200.0,
          "poly_price": 0.37,
          "kalshi_price": 0.08,
          "cost": 0.45,
          "profit_pct": 122.2,
          "dead_zone": 127.54,
          "units": 5,
          "deploy_dollars": 2.25,
          "kalshi_vol": 147876.14,
          "close_time": "2026-06-14T14:00:00Z",
          "qualified": false,
          "block_reason": "DZ $128 > max $40"
        },
        {
          "direction": "DOWN + YES",
          "kalshi_level": 64400.0,
          "poly_price": 0.64,
          "kalshi_price": 0.03,
          "cost": 0.67,
          "profit_pct": 49.3,
          "dead_zone": 72.46,
          "units": 5,
          "deploy_dollars": 3.35,
          "kalshi_vol": 143918.4,
          "close_time": "2026-06-14T14:00:00Z",
          "qualified": false,
          "block_reason": "DZ $72 > max $40"
        }
      ]
    },
    {
      "asset": "ETH",
      "price": 1666.0,
      "poly_up": 0.37,
      "poly_down": 0.65,
      "poly_open": 1666.9,
      "kalshi_levels": 75,
      "kalshi_raw": [
        {
          "t": 910.0,
          "ya": 1.0,
          "na": 0.01
        },
        {
          "t": 930.0,
          "ya": 1.0,
          "na": 0.01
        },
        {
          "t": 950.0,
          "ya": 1.0,
          "na": 0.01
        },
        {
          "t": 970.0,
          "ya": 1.0,
          "na": 0.01
        },
        {
          "t": 990.0,
          "ya": 1.0,
          "na": 0.01
        },
        {
          "t": 1010.0,
          "ya": 1.0,
          "na": 0.01
        },
        {
          "t": 1030.0,
          "ya": 1.0,
          "na": 0.01
        },
        {
          "t": 1050.0,
          "ya": 1.0,
          "na": 0.01
        },
        {
          "t": 1070.0,
          "ya": 1.0,
          "na": 0.01
        },
        {
          "t": 1090.0,
          "ya": 1.0,
          "na": 0.01
        },
        {
          "t": 1110.0,
          "ya": 1.0,
          "na": 0.01
        },
        {
          "t": 1130.0,
          "ya": 1.0,
          "na": 0.01
        },
        {
          "t": 1150.0,
          "ya": 1.0,
          "na": 0.01
        },
        {
          "t": 1170.0,
          "ya": 1.0,
          "na": 0.01
        },
        {
          "t": 1190.0,
          "ya": 1.0,
          "na": 0.01
        },
        {
          "t": 1210.0,
          "ya": 1.0,
          "na": 0.01
        },
        {
          "t": 1230.0,
          "ya": 1.0,
          "na": 0.01
        },
        {
          "t": 1250.0,
          "ya": 1.0,
          "na": 0.01
        },
        {
          "t": 1270.0,
          "ya": 1.0,
          "na": 0.01
        },
        {
          "t": 1290.0,
          "ya": 1.0,
          "na": 0.01
        },
        {
          "t": 1310.0,
          "ya": 1.0,
          "na": 0.01
        },
        {
          "t": 1330.0,
          "ya": 1.0,
          "na": 0.01
        },
        {
          "t": 1350.0,
          "ya": 1.0,
          "na": 0.01
        },
        {
          "t": 1370.0,
          "ya": 1.0,
          "na": 0.01
        },
        {
          "t": 1390.0,
          "ya": 1.0,
          "na": 0.01
        },
        {
          "t": 1410.0,
          "ya": 1.0,
          "na": 0.01
        },
        {
          "t": 1430.0,
          "ya": 1.0,
          "na": 0.01
        },
        {
          "t": 1450.0,
          "ya": 1.0,
          "na": 0.01
        },
        {
          "t": 1470.0,
          "ya": 1.0,
          "na": 0.01
        },
        {
          "t": 1490.0,
          "ya": 1.0,
          "na": 0.01
        },
        {
          "t": 1510.0,
          "ya": 1.0,
          "na": 0.01
        },
        {
          "t": 1530.0,
          "ya": 1.0,
          "na": 0.01
        },
        {
          "t": 1550.0,
          "ya": 1.0,
          "na": 0.01
        },
        {
          "t": 1570.0,
          "ya": 1.0,
          "na": 0.01
        },
        {
          "t": 1590.0,
          "ya": 1.0,
          "na": 0.01
        },
        {
          "t": 1610.0,
          "ya": 1.0,
          "na": 0.01
        },
        {
          "t": 1630.0,
          "ya": 1.0,
          "na": 0.01
        },
        {
          "t": 1650.0,
          "ya": 1.0,
          "na": 0.01
        },
        {
          "t": 1670.0,
          "ya": 0.04,
          "na": 0.99
        },
        {
          "t": 1690.0,
          "ya": 0.01,
          "na": 1.0
        },
        {
          "t": 1710.0,
          "ya": 0.01,
          "na": 1.0
        },
        {
          "t": 1730.0,
          "ya": 0.01,
          "na": 1.0
        },
        {
          "t": 1750.0,
          "ya": 0.01,
          "na": 1.0
        },
        {
          "t": 1770.0,
          "ya": 0.01,
          "na": 1.0
        },
        {
          "t": 1790.0,
          "ya": 0.01,
          "na": 1.0
        },
        {
          "t": 1810.0,
          "ya": 0.01,
          "na": 1.0
        },
        {
          "t": 1830.0,
          "ya": 0.01,
          "na": 1.0
        },
        {
          "t": 1850.0,
          "ya": 0.01,
          "na": 1.0
        },
        {
          "t": 1870.0,
          "ya": 0.01,
          "na": 1.0
        },
        {
          "t": 1890.0,
          "ya": 0.01,
          "na": 1.0
        },
        {
          "t": 1910.0,
          "ya": 0.01,
          "na": 1.0
        },
        {
          "t": 1930.0,
          "ya": 0.01,
          "na": 1.0
        },
        {
          "t": 1950.0,
          "ya": 0.01,
          "na": 1.0
        },
        {
          "t": 1970.0,
          "ya": 0.01,
          "na": 1.0
        },
        {
          "t": 1990.0,
          "ya": 0.01,
          "na": 1.0
        },
        {
          "t": 2010.0,
          "ya": 0.01,
          "na": 1.0
        },
        {
          "t": 2030.0,
          "ya": 0.01,
          "na": 1.0
        },
        {
          "t": 2050.0,
          "ya": 0.01,
          "na": 1.0
        },
        {
          "t": 2070.0,
          "ya": 0.01,
          "na": 1.0
        },
        {
          "t": 2090.0,
          "ya": 0.01,
          "na": 1.0
        },
        {
          "t": 2110.0,
          "ya": 0.01,
          "na": 1.0
        },
        {
          "t": 2130.0,
          "ya": 0.01,
          "na": 1.0
        },
        {
          "t": 2150.0,
          "ya": 0.01,
          "na": 1.0
        },
        {
          "t": 2170.0,
          "ya": 0.01,
          "na": 1.0
        },
        {
          "t": 2190.0,
          "ya": 0.01,
          "na": 1.0
        },
        {
          "t": 2210.0,
          "ya": 0.01,
          "na": 1.0
        },
        {
          "t": 2230.0,
          "ya": 0.01,
          "na": 1.0
        },
        {
          "t": 2250.0,
          "ya": 0.01,
          "na": 1.0
        },
        {
          "t": 2270.0,
          "ya": 0.01,
          "na": 1.0
        },
        {
          "t": 2290.0,
          "ya": 0.01,
          "na": 1.0
        },
        {
          "t": 2310.0,
          "ya": 0.01,
          "na": 1.0
        },
        {
          "t": 2330.0,
          "ya": 0.01,
          "na": 1.0
        },
        {
          "t": 2350.0,
          "ya": 0.01,
          "na": 1.0
        },
        {
          "t": 2370.0,
          "ya": 0.01,
          "na": 1.0
        },
        {
          "t": 2390.0,
          "ya": 0.01,
          "na": 1.0
        }
      ],
      "trades": [
        {
          "direction": "UP + NO",
          "kalshi_level": 1650.0,
          "poly_price": 0.37,
          "kalshi_price": 0.01,
          "cost": 0.38,
          "profit_pct": 163.2,
          "dead_zone": 16.9,
          "units": 5,
          "deploy_dollars": 1.9,
          "kalshi_vol": 1962.55,
          "close_time": null,
          "qualified": true,
          "block_reason": null
        },
        {
          "direction": "DOWN + YES",
          "kalshi_level": 1670.0,
          "poly_price": 0.65,
          "kalshi_price": 0.04,
          "cost": 0.69,
          "profit_pct": 44.9,
          "dead_zone": 3.1,
          "units": 5,
          "deploy_dollars": 3.45,
          "kalshi_vol": 7314.02,
          "close_time": null,
          "qualified": true,
          "block_reason": null
        }
      ]
    }
  ]
}