{
  "updated_at": "2026-04-21T10:35:07.516638+00:00",
  "assets": [
    {
      "asset": "BTC",
      "price": 76527.99,
      "poly_up": 0.89,
      "poly_down": 0.12,
      "poly_open": 76362.78,
      "kalshi_levels": 12,
      "kalshi_raw": [
        {
          "t": 76100.0,
          "ya": 0.98,
          "na": 0.03
        },
        {
          "t": 76200.0,
          "ya": 0.98,
          "na": 0.03
        },
        {
          "t": 76300.0,
          "ya": 0.97,
          "na": 0.04
        },
        {
          "t": 76400.0,
          "ya": 0.92,
          "na": 0.1
        },
        {
          "t": 76500.0,
          "ya": 0.71,
          "na": 0.3
        },
        {
          "t": 76600.0,
          "ya": 0.4,
          "na": 0.62
        },
        {
          "t": 76700.0,
          "ya": 0.16,
          "na": 0.85
        },
        {
          "t": 76800.0,
          "ya": 0.08,
          "na": 0.96
        },
        {
          "t": 76900.0,
          "ya": 0.03,
          "na": 0.98
        },
        {
          "t": 77000.0,
          "ya": 0.02,
          "na": 0.99
        },
        {
          "t": 77100.0,
          "ya": 0.02,
          "na": 0.99
        },
        {
          "t": 77200.0,
          "ya": 0.03,
          "na": 1.0
        }
      ],
      "trades": [
        {
          "direction": "UP + NO",
          "kalshi_level": 76400.0,
          "poly_price": 0.89,
          "kalshi_price": 0.1,
          "cost": 0.99,
          "profit_pct": 1.0,
          "dead_zone": 0.0,
          "units": 5,
          "deploy_dollars": 4.95,
          "kalshi_vol": 15835.49,
          "close_time": "2026-04-21T11:00:00Z",
          "qualified": false,
          "block_reason": "profit 1.0% < min 12%"
        },
        {
          "direction": "DOWN + YES",
          "kalshi_level": 76500.0,
          "poly_price": 0.12,
          "kalshi_price": 0.71,
          "cost": 0.83,
          "profit_pct": 20.5,
          "dead_zone": 137.22,
          "units": 5,
          "deploy_dollars": 4.15,
          "kalshi_vol": 31001.12,
          "close_time": "2026-04-21T11:00:00Z",
          "qualified": false,
          "block_reason": "DZ $137 > max $40"
        }
      ]
    },
    {
      "asset": "ETH",
      "price": 2329.05,
      "poly_up": 0.77,
      "poly_down": 0.24,
      "poly_open": 2325.7,
      "kalshi_levels": 75,
      "kalshi_raw": [
        {
          "t": 1509.99,
          "ya": 1.0,
          "na": 0.01
        },
        {
          "t": 1529.99,
          "ya": 1.0,
          "na": 0.01
        },
        {
          "t": 1549.99,
          "ya": 1.0,
          "na": 0.01
        },
        {
          "t": 1569.99,
          "ya": 1.0,
          "na": 0.01
        },
        {
          "t": 1589.99,
          "ya": 1.0,
          "na": 0.01
        },
        {
          "t": 1609.99,
          "ya": 1.0,
          "na": 0.01
        },
        {
          "t": 1629.99,
          "ya": 1.0,
          "na": 0.01
        },
        {
          "t": 1649.99,
          "ya": 1.0,
          "na": 0.01
        },
        {
          "t": 1669.99,
          "ya": 1.0,
          "na": 0.01
        },
        {
          "t": 1689.99,
          "ya": 1.0,
          "na": 0.01
        },
        {
          "t": 1709.99,
          "ya": 1.0,
          "na": 0.01
        },
        {
          "t": 1729.99,
          "ya": 1.0,
          "na": 0.01
        },
        {
          "t": 1749.99,
          "ya": 1.0,
          "na": 0.01
        },
        {
          "t": 1769.99,
          "ya": 1.0,
          "na": 0.01
        },
        {
          "t": 1789.99,
          "ya": 1.0,
          "na": 0.01
        },
        {
          "t": 1809.99,
          "ya": 1.0,
          "na": 0.01
        },
        {
          "t": 1829.99,
          "ya": 1.0,
          "na": 0.01
        },
        {
          "t": 1849.99,
          "ya": 1.0,
          "na": 0.01
        },
        {
          "t": 1869.99,
          "ya": 1.0,
          "na": 0.01
        },
        {
          "t": 1889.99,
          "ya": 1.0,
          "na": 0.01
        },
        {
          "t": 1909.99,
          "ya": 1.0,
          "na": 0.01
        },
        {
          "t": 1929.99,
          "ya": 1.0,
          "na": 0.01
        },
        {
          "t": 1949.99,
          "ya": 1.0,
          "na": 0.01
        },
        {
          "t": 1969.99,
          "ya": 1.0,
          "na": 0.01
        },
        {
          "t": 1989.99,
          "ya": 1.0,
          "na": 0.01
        },
        {
          "t": 2009.99,
          "ya": 1.0,
          "na": 0.01
        },
        {
          "t": 2029.99,
          "ya": 1.0,
          "na": 0.01
        },
        {
          "t": 2049.99,
          "ya": 1.0,
          "na": 0.01
        },
        {
          "t": 2069.99,
          "ya": 1.0,
          "na": 0.01
        },
        {
          "t": 2089.99,
          "ya": 1.0,
          "na": 0.01
        },
        {
          "t": 2109.99,
          "ya": 1.0,
          "na": 0.01
        },
        {
          "t": 2129.99,
          "ya": 1.0,
          "na": 0.01
        },
        {
          "t": 2149.99,
          "ya": 1.0,
          "na": 0.01
        },
        {
          "t": 2169.99,
          "ya": 1.0,
          "na": 0.01
        },
        {
          "t": 2189.99,
          "ya": 1.0,
          "na": 0.01
        },
        {
          "t": 2209.99,
          "ya": 1.0,
          "na": 0.01
        },
        {
          "t": 2229.99,
          "ya": 1.0,
          "na": 0.01
        },
        {
          "t": 2249.99,
          "ya": 1.0,
          "na": 0.01
        },
        {
          "t": 2269.99,
          "ya": 1.0,
          "na": 0.01
        },
        {
          "t": 2289.99,
          "ya": 1.0,
          "na": 0.05
        },
        {
          "t": 2309.99,
          "ya": 1.0,
          "na": 0.01
        },
        {
          "t": 2329.99,
          "ya": 0.56,
          "na": 0.55
        },
        {
          "t": 2349.99,
          "ya": 0.05,
          "na": 1.0
        },
        {
          "t": 2369.99,
          "ya": 0.08,
          "na": 1.0
        },
        {
          "t": 2389.99,
          "ya": 0.08,
          "na": 1.0
        },
        {
          "t": 2409.99,
          "ya": 0.01,
          "na": 1.0
        },
        {
          "t": 2429.99,
          "ya": 0.01,
          "na": 1.0
        },
        {
          "t": 2449.99,
          "ya": 0.01,
          "na": 1.0
        },
        {
          "t": 2469.99,
          "ya": 0.01,
          "na": 1.0
        },
        {
          "t": 2489.99,
          "ya": 0.01,
          "na": 1.0
        },
        {
          "t": 2509.99,
          "ya": 0.01,
          "na": 1.0
        },
        {
          "t": 2529.99,
          "ya": 0.01,
          "na": 1.0
        },
        {
          "t": 2549.99,
          "ya": 0.01,
          "na": 1.0
        },
        {
          "t": 2569.99,
          "ya": 0.01,
          "na": 1.0
        },
        {
          "t": 2589.99,
          "ya": 0.01,
          "na": 1.0
        },
        {
          "t": 2609.99,
          "ya": 0.01,
          "na": 1.0
        },
        {
          "t": 2629.99,
          "ya": 0.01,
          "na": 1.0
        },
        {
          "t": 2649.99,
          "ya": 0.01,
          "na": 1.0
        },
        {
          "t": 2669.99,
          "ya": 0.01,
          "na": 1.0
        },
        {
          "t": 2689.99,
          "ya": 0.01,
          "na": 1.0
        },
        {
          "t": 2709.99,
          "ya": 0.01,
          "na": 1.0
        },
        {
          "t": 2729.99,
          "ya": 0.01,
          "na": 1.0
        },
        {
          "t": 2749.99,
          "ya": 0.01,
          "na": 1.0
        },
        {
          "t": 2769.99,
          "ya": 0.01,
          "na": 1.0
        },
        {
          "t": 2789.99,
          "ya": 0.01,
          "na": 1.0
        },
        {
          "t": 2809.99,
          "ya": 0.01,
          "na": 1.0
        },
        {
          "t": 2829.99,
          "ya": 0.01,
          "na": 1.0
        },
        {
          "t": 2849.99,
          "ya": 0.01,
          "na": 1.0
        },
        {
          "t": 2869.99,
          "ya": 0.01,
          "na": 1.0
        },
        {
          "t": 2889.99,
          "ya": 0.01,
          "na": 1.0
        },
        {
          "t": 2909.99,
          "ya": 0.01,
          "na": 1.0
        },
        {
          "t": 2929.99,
          "ya": 0.01,
          "na": 1.0
        },
        {
          "t": 2949.99,
          "ya": 0.01,
          "na": 1.0
        },
        {
          "t": 2969.99,
          "ya": 0.01,
          "na": 1.0
        },
        {
          "t": 2989.99,
          "ya": 0.01,
          "na": 1.0
        }
      ],
      "trades": [
        {
          "direction": "UP + NO",
          "kalshi_level": 2309.99,
          "poly_price": 0.77,
          "kalshi_price": 0.01,
          "cost": 0.78,
          "profit_pct": 28.2,
          "dead_zone": 15.71,
          "units": 5,
          "deploy_dollars": 3.9,
          "kalshi_vol": 26.0,
          "close_time": "2026-04-21T11:00:00Z",
          "qualified": true,
          "block_reason": null
        },
        {
          "direction": "DOWN + YES",
          "kalshi_level": 2329.99,
          "poly_price": 0.24,
          "kalshi_price": 0.56,
          "cost": 0.8,
          "profit_pct": 25.0,
          "dead_zone": 4.29,
          "units": 5,
          "deploy_dollars": 4.0,
          "kalshi_vol": 795.62,
          "close_time": "2026-04-21T11:00:00Z",
          "qualified": true,
          "block_reason": null
        }
      ]
    }
  ]
}