{
  "updated_at": "2026-04-23T21:05:06.560672+00:00",
  "assets": [
    {
      "asset": "BTC",
      "price": 77854.71,
      "poly_up": 0.45,
      "poly_down": 0.56,
      "poly_open": 77886.97,
      "kalshi_levels": 23,
      "kalshi_raw": [
        {
          "t": 76100.0,
          "ya": 1.0,
          "na": 0.72
        },
        {
          "t": 76200.0,
          "ya": 1.0,
          "na": 0.64
        },
        {
          "t": 76300.0,
          "ya": 1.0,
          "na": 0.23
        },
        {
          "t": 76400.0,
          "ya": 1.0,
          "na": 0.22
        },
        {
          "t": 76500.0,
          "ya": 1.0,
          "na": 0.2
        },
        {
          "t": 76600.0,
          "ya": 1.0,
          "na": 0.75
        },
        {
          "t": 77200.0,
          "ya": 0.99,
          "na": 0.02
        },
        {
          "t": 77300.0,
          "ya": 0.99,
          "na": 0.02
        },
        {
          "t": 77400.0,
          "ya": 0.97,
          "na": 0.04
        },
        {
          "t": 77500.0,
          "ya": 0.93,
          "na": 0.08
        },
        {
          "t": 77600.0,
          "ya": 0.87,
          "na": 0.14
        },
        {
          "t": 77700.0,
          "ya": 0.77,
          "na": 0.24
        },
        {
          "t": 77800.0,
          "ya": 0.62,
          "na": 0.39
        },
        {
          "t": 77900.0,
          "ya": 0.45,
          "na": 0.56
        },
        {
          "t": 78000.0,
          "ya": 0.31,
          "na": 0.7
        },
        {
          "t": 78100.0,
          "ya": 0.18,
          "na": 0.83
        },
        {
          "t": 78200.0,
          "ya": 0.09,
          "na": 0.92
        },
        {
          "t": 78300.0,
          "ya": 0.06,
          "na": 0.95
        },
        {
          "t": 78400.0,
          "ya": 0.03,
          "na": 0.98
        },
        {
          "t": 78500.0,
          "ya": 0.02,
          "na": 0.99
        },
        {
          "t": 78600.0,
          "ya": 0.02,
          "na": 0.99
        },
        {
          "t": 79200.0,
          "ya": 0.02,
          "na": 1.0
        },
        {
          "t": 79400.0,
          "ya": 0.04,
          "na": 1.0
        }
      ],
      "trades": [
        {
          "direction": "UP + NO",
          "kalshi_level": 77800.0,
          "poly_price": 0.45,
          "kalshi_price": 0.39,
          "cost": 0.84,
          "profit_pct": 19.0,
          "dead_zone": 86.97,
          "units": 5,
          "deploy_dollars": 4.2,
          "kalshi_vol": 4958.32,
          "close_time": "2026-04-23T22:00:00Z",
          "qualified": false,
          "block_reason": "DZ $87 > max $40"
        },
        {
          "direction": "DOWN + YES",
          "kalshi_level": 78000.0,
          "poly_price": 0.56,
          "kalshi_price": 0.31,
          "cost": 0.87,
          "profit_pct": 14.9,
          "dead_zone": 113.03,
          "units": 5,
          "deploy_dollars": 4.35,
          "kalshi_vol": 5784.26,
          "close_time": "2026-04-23T22:00:00Z",
          "qualified": false,
          "block_reason": "DZ $113 > max $40"
        }
      ]
    },
    {
      "asset": "ETH",
      "price": 2325.1,
      "poly_up": 0.49,
      "poly_down": 0.52,
      "poly_open": 2325.36,
      "kalshi_levels": 75,
      "kalshi_raw": [
        {
          "t": 1609.99,
          "ya": 1.0,
          "na": 0.01
        },
        {
          "t": 1629.99,
          "ya": 1.0,
          "na": 0.01
        },
        {
          "t": 1649.99,
          "ya": 1.0,
          "na": 0.01
        },
        {
          "t": 1669.99,
          "ya": 1.0,
          "na": 0.01
        },
        {
          "t": 1689.99,
          "ya": 1.0,
          "na": 0.01
        },
        {
          "t": 1709.99,
          "ya": 1.0,
          "na": 0.01
        },
        {
          "t": 1729.99,
          "ya": 1.0,
          "na": 0.01
        },
        {
          "t": 1749.99,
          "ya": 1.0,
          "na": 0.01
        },
        {
          "t": 1769.99,
          "ya": 1.0,
          "na": 0.01
        },
        {
          "t": 1789.99,
          "ya": 1.0,
          "na": 0.01
        },
        {
          "t": 1809.99,
          "ya": 1.0,
          "na": 0.01
        },
        {
          "t": 1829.99,
          "ya": 1.0,
          "na": 0.01
        },
        {
          "t": 1849.99,
          "ya": 1.0,
          "na": 0.01
        },
        {
          "t": 1869.99,
          "ya": 1.0,
          "na": 0.01
        },
        {
          "t": 1889.99,
          "ya": 1.0,
          "na": 0.01
        },
        {
          "t": 1909.99,
          "ya": 1.0,
          "na": 0.01
        },
        {
          "t": 1929.99,
          "ya": 1.0,
          "na": 0.01
        },
        {
          "t": 1949.99,
          "ya": 1.0,
          "na": 0.01
        },
        {
          "t": 1969.99,
          "ya": 1.0,
          "na": 0.01
        },
        {
          "t": 1989.99,
          "ya": 1.0,
          "na": 0.01
        },
        {
          "t": 2009.99,
          "ya": 1.0,
          "na": 0.01
        },
        {
          "t": 2029.99,
          "ya": 1.0,
          "na": 0.01
        },
        {
          "t": 2049.99,
          "ya": 1.0,
          "na": 0.01
        },
        {
          "t": 2069.99,
          "ya": 1.0,
          "na": 0.01
        },
        {
          "t": 2089.99,
          "ya": 1.0,
          "na": 0.01
        },
        {
          "t": 2109.99,
          "ya": 1.0,
          "na": 0.01
        },
        {
          "t": 2129.99,
          "ya": 1.0,
          "na": 0.01
        },
        {
          "t": 2149.99,
          "ya": 1.0,
          "na": 0.01
        },
        {
          "t": 2169.99,
          "ya": 1.0,
          "na": 0.01
        },
        {
          "t": 2189.99,
          "ya": 1.0,
          "na": 0.03
        },
        {
          "t": 2209.99,
          "ya": 1.0,
          "na": 0.03
        },
        {
          "t": 2229.99,
          "ya": 1.0,
          "na": 0.02
        },
        {
          "t": 2249.99,
          "ya": 1.0,
          "na": 0.02
        },
        {
          "t": 2269.99,
          "ya": 1.0,
          "na": 0.01
        },
        {
          "t": 2289.99,
          "ya": 1.0,
          "na": 0.01
        },
        {
          "t": 2309.99,
          "ya": 0.91,
          "na": 0.17
        },
        {
          "t": 2329.99,
          "ya": 0.33,
          "na": 0.79
        },
        {
          "t": 2349.99,
          "ya": 0.01,
          "na": 1.0
        },
        {
          "t": 2369.99,
          "ya": 0.01,
          "na": 1.0
        },
        {
          "t": 2389.99,
          "ya": 0.02,
          "na": 1.0
        },
        {
          "t": 2409.99,
          "ya": 0.02,
          "na": 1.0
        },
        {
          "t": 2429.99,
          "ya": 0.02,
          "na": 1.0
        },
        {
          "t": 2449.99,
          "ya": 0.01,
          "na": 1.0
        },
        {
          "t": 2469.99,
          "ya": 0.01,
          "na": 1.0
        },
        {
          "t": 2489.99,
          "ya": 0.01,
          "na": 1.0
        },
        {
          "t": 2509.99,
          "ya": 0.01,
          "na": 1.0
        },
        {
          "t": 2529.99,
          "ya": 0.01,
          "na": 1.0
        },
        {
          "t": 2549.99,
          "ya": 0.01,
          "na": 1.0
        },
        {
          "t": 2569.99,
          "ya": 0.01,
          "na": 1.0
        },
        {
          "t": 2589.99,
          "ya": 0.01,
          "na": 1.0
        },
        {
          "t": 2609.99,
          "ya": 0.01,
          "na": 1.0
        },
        {
          "t": 2629.99,
          "ya": 0.01,
          "na": 1.0
        },
        {
          "t": 2649.99,
          "ya": 0.01,
          "na": 1.0
        },
        {
          "t": 2669.99,
          "ya": 0.01,
          "na": 1.0
        },
        {
          "t": 2689.99,
          "ya": 0.01,
          "na": 1.0
        },
        {
          "t": 2709.99,
          "ya": 0.01,
          "na": 1.0
        },
        {
          "t": 2729.99,
          "ya": 0.01,
          "na": 1.0
        },
        {
          "t": 2749.99,
          "ya": 0.01,
          "na": 1.0
        },
        {
          "t": 2769.99,
          "ya": 0.01,
          "na": 1.0
        },
        {
          "t": 2789.99,
          "ya": 0.01,
          "na": 1.0
        },
        {
          "t": 2809.99,
          "ya": 0.01,
          "na": 1.0
        },
        {
          "t": 2829.99,
          "ya": 0.01,
          "na": 1.0
        },
        {
          "t": 2849.99,
          "ya": 0.01,
          "na": 1.0
        },
        {
          "t": 2869.99,
          "ya": 0.01,
          "na": 1.0
        },
        {
          "t": 2889.99,
          "ya": 0.01,
          "na": 1.0
        },
        {
          "t": 2909.99,
          "ya": 0.01,
          "na": 1.0
        },
        {
          "t": 2929.99,
          "ya": 0.01,
          "na": 1.0
        },
        {
          "t": 2949.99,
          "ya": 0.01,
          "na": 1.0
        },
        {
          "t": 2969.99,
          "ya": 0.01,
          "na": 1.0
        },
        {
          "t": 2989.99,
          "ya": 0.01,
          "na": 1.0
        },
        {
          "t": 3009.99,
          "ya": 0.01,
          "na": 1.0
        },
        {
          "t": 3029.99,
          "ya": 0.01,
          "na": 1.0
        },
        {
          "t": 3049.99,
          "ya": 0.01,
          "na": 1.0
        },
        {
          "t": 3069.99,
          "ya": 0.01,
          "na": 1.0
        },
        {
          "t": 3089.99,
          "ya": 0.01,
          "na": 1.0
        }
      ],
      "trades": [
        {
          "direction": "UP + NO",
          "kalshi_level": 2309.99,
          "poly_price": 0.49,
          "kalshi_price": 0.17,
          "cost": 0.66,
          "profit_pct": 51.5,
          "dead_zone": 15.37,
          "units": 5,
          "deploy_dollars": 3.3,
          "kalshi_vol": 1041.0,
          "close_time": "2026-04-23T22:00:00Z",
          "qualified": true,
          "block_reason": null
        },
        {
          "direction": "DOWN + YES",
          "kalshi_level": 2329.99,
          "poly_price": 0.52,
          "kalshi_price": 0.33,
          "cost": 0.85,
          "profit_pct": 17.6,
          "dead_zone": 4.63,
          "units": 5,
          "deploy_dollars": 4.25,
          "kalshi_vol": 38.0,
          "close_time": "2026-04-23T22:00:00Z",
          "qualified": true,
          "block_reason": null
        }
      ]
    }
  ]
}